{
    "id": "13cfa1a7-f6cf-4880-bbcf-1cd41cec98ab",
    "problem_id": "C2E",
    "language": "python",
    "code": "n = int(input().spli())\nprint(n >> 1)",
    "results": [
        {
            "case": "samples/sample1",
            "status": "Wrong Answer",
            "stdout": "",
            "stderr": ""
        },
        {
            "case": "testcases/1",
            "status": "Wrong Answer",
            "stdout": "",
            "stderr": ""
        },
        {
            "case": "testcases/10",
            "status": "Wrong Answer",
            "stdout": "",
            "stderr": ""
        },
        {
            "case": "testcases/11",
            "status": "Wrong Answer",
            "stdout": "",
            "stderr": ""
        },
        {
            "case": "testcases/12",
            "status": "Wrong Answer",
            "stdout": "",
            "stderr": ""
        },
        {
            "case": "testcases/2",
            "status": "Wrong Answer",
            "stdout": "",
            "stderr": ""
        },
        {
            "case": "testcases/3",
            "status": "Wrong Answer",
            "stdout": "",
            "stderr": ""
        },
        {
            "case": "testcases/4",
            "status": "Wrong Answer",
            "stdout": "",
            "stderr": ""
        },
        {
            "case": "testcases/5",
            "status": "Wrong Answer",
            "stdout": "",
            "stderr": ""
        },
        {
            "case": "testcases/6",
            "status": "Wrong Answer",
            "stdout": "",
            "stderr": ""
        },
        {
            "case": "testcases/7",
            "status": "Wrong Answer",
            "stdout": "",
            "stderr": ""
        },
        {
            "case": "testcases/8",
            "status": "Wrong Answer",
            "stdout": "",
            "stderr": ""
        },
        {
            "case": "testcases/9",
            "status": "Wrong Answer",
            "stdout": "",
            "stderr": ""
        }
    ],
    "timestamp": "2025-11-03T19:41:09.692210"
}